nonebot_plugin_mcplayer/__init__.py
nonebot_plugin_mcplayer/bind.py
nonebot_plugin_mcplayer/config.py
nonebot_plugin_mcplayer/status.py
nonebot_plugin_mcplayer-2.0.0.dist-info/LICENSE.txt
nonebot_plugin_mcplayer-2.0.0.dist-info/METADATA
nonebot_plugin_mcplayer-2.0.0.dist-info/WHEEL
nonebot_plugin_mcplayer-2.0.0.dist-info/top_level.txt
nonebot_plugin_mcplayer-2.0.0.dist-info/RECORD
