Metadata-Version: 2.1
Name: nonebot-plugin-mcplayer
Version: 2.0.0
Summary: 基于OneBot适配器的NoneBot2查看MC服务器在线玩家信息与服务器状态的插件
Home-page: https://github.com/SkyDynamic/nonebot_plugin_mcplayer
Author: Sky_Dynamic
Author-email: SkyDynamic@outlook.com
Keywords: pip,nonebot2,nonebot,nonebot_plugin,mcplayer
Platform: any
Classifier: Programming Language :: Python :: 3
Classifier: License :: OSI Approved :: MIT License
Classifier: Operating System :: OS Independent
Requires-Python: >=3.7.3
License-File: LICENSE.txt
Requires-Dist: nonebot2 (>=2.0.0rc2)
Requires-Dist: nonebot-adapter-onebot (>=2.1.5)
Requires-Dist: mcstatus (>=10.0.1)
